openslides_presenter/__init__.py
openslides_presenter/apps.py
openslides_presenter/views.py
openslides_presenter/static/css/presenter.css
openslides_presenter/static/js/openslides_presenter/base.js
openslides_presenter/static/js/openslides_presenter/site.js
openslides_presenter/static/templates/openslides_presenter/presenter.html
openslides_presenter-2.0.3.dist-info/METADATA
openslides_presenter-2.0.3.dist-info/RECORD
openslides_presenter-2.0.3.dist-info/WHEEL
openslides_presenter-2.0.3.dist-info/entry_points.txt
openslides_presenter-2.0.3.dist-info/top_level.txt
